{"downloadLink":"","azanSettings":{"fajrIqama":25,"fajrPrayDuration":10,"zuhrIqama":20,"zuhrPrayDurarion":5,"asrIqama":20,"asrPrayDuration":5,"magribIqama":5,"magribPrayDuration":10,"ishaIqama":20,"ishaPrayDuration":5,"fridayIqama":20,"fridayPrayDuration":5},"prayerData":[{"pid":183637,"gDate":"2026-02-01T00:00:00","dayofWeek":"Sunday","hijryDay":13,"hijryMonth":8,"hijryYear":1447,"emsak":"2026-02-01T05:39:00","fajr":"2026-02-01T05:39:00","shurooq":"2026-02-01T06:55:00","zuhr":"2026-02-01T12:31:00","asr":"2026-02-01T15:37:00","maghrib":"2026-02-01T18:02:00","isha":"2026-02-01T19:18:00","comments":"الفجيرةCreated from Application Parser","areaNameAr":"الفجيرة","areaNameEn":"Fujairah","emirateNameAr":"الفجيرة","emirateNameEn":"Fujairah","areaID":52,"emirateID":7,"hijryMonthNameEn":"Shaban","hijryMonthNameAr":"شعبان","gMonthNameEn":"February","gMonthNameAr":"فبراير"},{"pid":183697,"gDate":"2026-02-02T00:00:00","dayofWeek":"Monday","hijryDay":14,"hijryMonth":8,"hijryYear":1447,"emsak":"2026-02-02T05:39:00","fajr":"2026-02-02T05:39:00","shurooq":"2026-02-02T06:54:00","zuhr":"2026-02-02T12:31:00","asr":"2026-02-02T15:38:00","maghrib":"2026-02-02T18:03:00","isha":"2026-02-02T19:19:00","comments":"الفجيرةCreated from Application Parser","areaNameAr":"الفجيرة","areaNameEn":"Fujairah","emirateNameAr":"الفجيرة","emirateNameEn":"Fujairah","areaID":52,"emirateID":7,"hijryMonthNameEn":"Shaban","hijryMonthNameAr":"شعبان","gMonthNameEn":"February","gMonthNameAr":"فبراير"},{"pid":183757,"gDate":"2026-02-03T00:00:00","dayofWeek":"Tuesday","hijryDay":15,"hijryMonth":8,"hijryYear":1447,"emsak":"2026-02-03T05:38:00","fajr":"2026-02-03T05:38:00","shurooq":"2026-02-03T06:54:00","zuhr":"2026-02-03T12:31:00","asr":"2026-02-03T15:38:00","maghrib":"2026-02-03T18:04:00","isha":"2026-02-03T19:19:00","comments":"الفجيرةCreated from Application Parser","areaNameAr":"الفجيرة","areaNameEn":"Fujairah","emirateNameAr":"الفجيرة","emirateNameEn":"Fujairah","areaID":52,"emirateID":7,"hijryMonthNameEn":"Shaban","hijryMonthNameAr":"شعبان","gMonthNameEn":"February","gMonthNameAr":"فبراير"},{"pid":183817,"gDate":"2026-02-04T00:00:00","dayofWeek":"Wednesday","hijryDay":16,"hijryMonth":8,"hijryYear":1447,"emsak":"2026-02-04T05:38:00","fajr":"2026-02-04T05:38:00","shurooq":"2026-02-04T06:53:00","zuhr":"2026-02-04T12:31:00","asr":"2026-02-04T15:39:00","maghrib":"2026-02-04T18:04:00","isha":"2026-02-04T19:20:00","comments":"الفجيرةCreated from Application Parser","areaNameAr":"الفجيرة","areaNameEn":"Fujairah","emirateNameAr":"الفجيرة","emirateNameEn":"Fujairah","areaID":52,"emirateID":7,"hijryMonthNameEn":"Shaban","hijryMonthNameAr":"شعبان","gMonthNameEn":"February","gMonthNameAr":"فبراير"},{"pid":183877,"gDate":"2026-02-05T00:00:00","dayofWeek":"Thursday","hijryDay":17,"hijryMonth":8,"hijryYear":1447,"emsak":"2026-02-05T05:37:00","fajr":"2026-02-05T05:37:00","shurooq":"2026-02-05T06:53:00","zuhr":"2026-02-05T12:31:00","asr":"2026-02-05T15:40:00","maghrib":"2026-02-05T18:05:00","isha":"2026-02-05T19:20:00","comments":"الفجيرةCreated from Application Parser","areaNameAr":"الفجيرة","areaNameEn":"Fujairah","emirateNameAr":"الفجيرة","emirateNameEn":"Fujairah","areaID":52,"emirateID":7,"hijryMonthNameEn":"Shaban","hijryMonthNameAr":"شعبان","gMonthNameEn":"February","gMonthNameAr":"فبراير"},{"pid":183937,"gDate":"2026-02-06T00:00:00","dayofWeek":"Friday","hijryDay":18,"hijryMonth":8,"hijryYear":1447,"emsak":"2026-02-06T05:37:00","fajr":"2026-02-06T05:37:00","shurooq":"2026-02-06T06:52:00","zuhr":"2026-02-06T12:31:00","asr":"2026-02-06T15:40:00","maghrib":"2026-02-06T18:06:00","isha":"2026-02-06T19:21:00","comments":"الفجيرةCreated from Application Parser","areaNameAr":"الفجيرة","areaNameEn":"Fujairah","emirateNameAr":"الفجيرة","emirateNameEn":"Fujairah","areaID":52,"emirateID":7,"hijryMonthNameEn":"Shaban","hijryMonthNameAr":"شعبان","gMonthNameEn":"February","gMonthNameAr":"فبراير"},{"pid":183997,"gDate":"2026-02-07T00:00:00","dayofWeek":"Saturday","hijryDay":19,"hijryMonth":8,"hijryYear":1447,"emsak":"2026-02-07T05:37:00","fajr":"2026-02-07T05:37:00","shurooq":"2026-02-07T06:52:00","zuhr":"2026-02-07T12:31:00","asr":"2026-02-07T15:41:00","maghrib":"2026-02-07T18:06:00","isha":"2026-02-07T19:22:00","comments":"الفجيرةCreated from Application Parser","areaNameAr":"الفجيرة","areaNameEn":"Fujairah","emirateNameAr":"الفجيرة","emirateNameEn":"Fujairah","areaID":52,"emirateID":7,"hijryMonthNameEn":"Shaban","hijryMonthNameAr":"شعبان","gMonthNameEn":"February","gMonthNameAr":"فبراير"},{"pid":184057,"gDate":"2026-02-08T00:00:00","dayofWeek":"Sunday","hijryDay":20,"hijryMonth":8,"hijryYear":1447,"emsak":"2026-02-08T05:36:00","fajr":"2026-02-08T05:36:00","shurooq":"2026-02-08T06:51:00","zuhr":"2026-02-08T12:31:00","asr":"2026-02-08T15:41:00","maghrib":"2026-02-08T18:07:00","isha":"2026-02-08T19:22:00","comments":"الفجيرةCreated from Application Parser","areaNameAr":"الفجيرة","areaNameEn":"Fujairah","emirateNameAr":"الفجيرة","emirateNameEn":"Fujairah","areaID":52,"emirateID":7,"hijryMonthNameEn":"Shaban","hijryMonthNameAr":"شعبان","gMonthNameEn":"February","gMonthNameAr":"فبراير"},{"pid":184117,"gDate":"2026-02-09T00:00:00","dayofWeek":"Monday","hijryDay":21,"hijryMonth":8,"hijryYear":1447,"emsak":"2026-02-09T05:36:00","fajr":"2026-02-09T05:36:00","shurooq":"2026-02-09T06:51:00","zuhr":"2026-02-09T12:31:00","asr":"2026-02-09T15:41:00","maghrib":"2026-02-09T18:08:00","isha":"2026-02-09T19:23:00","comments":"الفجيرةCreated from Application Parser","areaNameAr":"الفجيرة","areaNameEn":"Fujairah","emirateNameAr":"الفجيرة","emirateNameEn":"Fujairah","areaID":52,"emirateID":7,"hijryMonthNameEn":"Shaban","hijryMonthNameAr":"شعبان","gMonthNameEn":"February","gMonthNameAr":"فبراير"},{"pid":184177,"gDate":"2026-02-10T00:00:00","dayofWeek":"Tuesday","hijryDay":22,"hijryMonth":8,"hijryYear":1447,"emsak":"2026-02-10T05:35:00","fajr":"2026-02-10T05:35:00","shurooq":"2026-02-10T06:50:00","zuhr":"2026-02-10T12:31:00","asr":"2026-02-10T15:42:00","maghrib":"2026-02-10T18:08:00","isha":"2026-02-10T19:23:00","comments":"الفجيرةCreated from Application Parser","areaNameAr":"الفجيرة","areaNameEn":"Fujairah","emirateNameAr":"الفجيرة","emirateNameEn":"Fujairah","areaID":52,"emirateID":7,"hijryMonthNameEn":"Shaban","hijryMonthNameAr":"شعبان","gMonthNameEn":"February","gMonthNameAr":"فبراير"},{"pid":184237,"gDate":"2026-02-11T00:00:00","dayofWeek":"Wednesday","hijryDay":23,"hijryMonth":8,"hijryYear":1447,"emsak":"2026-02-11T05:35:00","fajr":"2026-02-11T05:35:00","shurooq":"2026-02-11T06:49:00","zuhr":"2026-02-11T12:31:00","asr":"2026-02-11T15:42:00","maghrib":"2026-02-11T18:09:00","isha":"2026-02-11T19:24:00","comments":"الفجيرةCreated from Application Parser","areaNameAr":"الفجيرة","areaNameEn":"Fujairah","emirateNameAr":"الفجيرة","emirateNameEn":"Fujairah","areaID":52,"emirateID":7,"hijryMonthNameEn":"Shaban","hijryMonthNameAr":"شعبان","gMonthNameEn":"February","gMonthNameAr":"فبراير"},{"pid":184297,"gDate":"2026-02-12T00:00:00","dayofWeek":"Thursday","hijryDay":24,"hijryMonth":8,"hijryYear":1447,"emsak":"2026-02-12T05:34:00","fajr":"2026-02-12T05:34:00","shurooq":"2026-02-12T06:49:00","zuhr":"2026-02-12T12:31:00","asr":"2026-02-12T15:43:00","maghrib":"2026-02-12T18:10:00","isha":"2026-02-12T19:24:00","comments":"الفجيرةCreated from Application Parser","areaNameAr":"الفجيرة","areaNameEn":"Fujairah","emirateNameAr":"الفجيرة","emirateNameEn":"Fujairah","areaID":52,"emirateID":7,"hijryMonthNameEn":"Shaban","hijryMonthNameAr":"شعبان","gMonthNameEn":"February","gMonthNameAr":"فبراير"},{"pid":184357,"gDate":"2026-02-13T00:00:00","dayofWeek":"Friday","hijryDay":25,"hijryMonth":8,"hijryYear":1447,"emsak":"2026-02-13T05:33:00","fajr":"2026-02-13T05:33:00","shurooq":"2026-02-13T06:48:00","zuhr":"2026-02-13T12:31:00","asr":"2026-02-13T15:43:00","maghrib":"2026-02-13T18:10:00","isha":"2026-02-13T19:25:00","comments":"الفجيرةCreated from Application Parser","areaNameAr":"الفجيرة","areaNameEn":"Fujairah","emirateNameAr":"الفجيرة","emirateNameEn":"Fujairah","areaID":52,"emirateID":7,"hijryMonthNameEn":"Shaban","hijryMonthNameAr":"شعبان","gMonthNameEn":"February","gMonthNameAr":"فبراير"},{"pid":184417,"gDate":"2026-02-14T00:00:00","dayofWeek":"Saturday","hijryDay":26,"hijryMonth":8,"hijryYear":1447,"emsak":"2026-02-14T05:33:00","fajr":"2026-02-14T05:33:00","shurooq":"2026-02-14T06:47:00","zuhr":"2026-02-14T12:31:00","asr":"2026-02-14T15:44:00","maghrib":"2026-02-14T18:11:00","isha":"2026-02-14T19:25:00","comments":"الفجيرةCreated from Application Parser","areaNameAr":"الفجيرة","areaNameEn":"Fujairah","emirateNameAr":"الفجيرة","emirateNameEn":"Fujairah","areaID":52,"emirateID":7,"hijryMonthNameEn":"Shaban","hijryMonthNameAr":"شعبان","gMonthNameEn":"February","gMonthNameAr":"فبراير"},{"pid":184477,"gDate":"2026-02-15T00:00:00","dayofWeek":"Sunday","hijryDay":27,"hijryMonth":8,"hijryYear":1447,"emsak":"2026-02-15T05:32:00","fajr":"2026-02-15T05:32:00","shurooq":"2026-02-15T06:47:00","zuhr":"2026-02-15T12:31:00","asr":"2026-02-15T15:44:00","maghrib":"2026-02-15T18:12:00","isha":"2026-02-15T19:26:00","comments":"الفجيرةCreated from Application Parser","areaNameAr":"الفجيرة","areaNameEn":"Fujairah","emirateNameAr":"الفجيرة","emirateNameEn":"Fujairah","areaID":52,"emirateID":7,"hijryMonthNameEn":"Shaban","hijryMonthNameAr":"شعبان","gMonthNameEn":"February","gMonthNameAr":"فبراير"},{"pid":184537,"gDate":"2026-02-16T00:00:00","dayofWeek":"Monday","hijryDay":28,"hijryMonth":8,"hijryYear":1447,"emsak":"2026-02-16T05:32:00","fajr":"2026-02-16T05:32:00","shurooq":"2026-02-16T06:46:00","zuhr":"2026-02-16T12:31:00","asr":"2026-02-16T15:44:00","maghrib":"2026-02-16T18:12:00","isha":"2026-02-16T19:27:00","comments":"الفجيرةCreated from Application Parser","areaNameAr":"الفجيرة","areaNameEn":"Fujairah","emirateNameAr":"الفجيرة","emirateNameEn":"Fujairah","areaID":52,"emirateID":7,"hijryMonthNameEn":"Shaban","hijryMonthNameAr":"شعبان","gMonthNameEn":"February","gMonthNameAr":"فبراير"},{"pid":184597,"gDate":"2026-02-17T00:00:00","dayofWeek":"Tuesday","hijryDay":29,"hijryMonth":8,"hijryYear":1447,"emsak":"2026-02-17T05:31:00","fajr":"2026-02-17T05:31:00","shurooq":"2026-02-17T06:45:00","zuhr":"2026-02-17T12:31:00","asr":"2026-02-17T15:45:00","maghrib":"2026-02-17T18:13:00","isha":"2026-02-17T19:27:00","comments":"الفجيرةCreated from Application Parser","areaNameAr":"الفجيرة","areaNameEn":"Fujairah","emirateNameAr":"الفجيرة","emirateNameEn":"Fujairah","areaID":52,"emirateID":7,"hijryMonthNameEn":"Shaban","hijryMonthNameAr":"شعبان","gMonthNameEn":"February","gMonthNameAr":"فبراير"},{"pid":184657,"gDate":"2026-02-18T00:00:00","dayofWeek":"Wednesday","hijryDay":1,"hijryMonth":9,"hijryYear":1447,"emsak":"2026-02-18T05:30:00","fajr":"2026-02-18T05:30:00","shurooq":"2026-02-18T06:44:00","zuhr":"2026-02-18T12:31:00","asr":"2026-02-18T15:45:00","maghrib":"2026-02-18T18:13:00","isha":"2026-02-18T19:28:00","comments":"الفجيرةCreated from Application Parser","areaNameAr":"الفجيرة","areaNameEn":"Fujairah","emirateNameAr":"الفجيرة","emirateNameEn":"Fujairah","areaID":52,"emirateID":7,"hijryMonthNameEn":"Ramadhan","hijryMonthNameAr":"رمضان","gMonthNameEn":"February","gMonthNameAr":"فبراير"},{"pid":184717,"gDate":"2026-02-19T00:00:00","dayofWeek":"Thursday","hijryDay":2,"hijryMonth":9,"hijryYear":1447,"emsak":"2026-02-19T05:30:00","fajr":"2026-02-19T05:30:00","shurooq":"2026-02-19T06:44:00","zuhr":"2026-02-19T12:31:00","asr":"2026-02-19T15:45:00","maghrib":"2026-02-19T18:14:00","isha":"2026-02-19T19:28:00","comments":"الفجيرةCreated from Application Parser","areaNameAr":"الفجيرة","areaNameEn":"Fujairah","emirateNameAr":"الفجيرة","emirateNameEn":"Fujairah","areaID":52,"emirateID":7,"hijryMonthNameEn":"Ramadhan","hijryMonthNameAr":"رمضان","gMonthNameEn":"February","gMonthNameAr":"فبراير"},{"pid":184777,"gDate":"2026-02-20T00:00:00","dayofWeek":"Friday","hijryDay":3,"hijryMonth":9,"hijryYear":1447,"emsak":"2026-02-20T05:29:00","fajr":"2026-02-20T05:29:00","shurooq":"2026-02-20T06:43:00","zuhr":"2026-02-20T12:31:00","asr":"2026-02-20T15:46:00","maghrib":"2026-02-20T18:15:00","isha":"2026-02-20T19:29:00","comments":"الفجيرةCreated from Application Parser","areaNameAr":"الفجيرة","areaNameEn":"Fujairah","emirateNameAr":"الفجيرة","emirateNameEn":"Fujairah","areaID":52,"emirateID":7,"hijryMonthNameEn":"Ramadhan","hijryMonthNameAr":"رمضان","gMonthNameEn":"February","gMonthNameAr":"فبراير"},{"pid":184837,"gDate":"2026-02-21T00:00:00","dayofWeek":"Saturday","hijryDay":4,"hijryMonth":9,"hijryYear":1447,"emsak":"2026-02-21T05:28:00","fajr":"2026-02-21T05:28:00","shurooq":"2026-02-21T06:42:00","zuhr":"2026-02-21T12:31:00","asr":"2026-02-21T15:46:00","maghrib":"2026-02-21T18:15:00","isha":"2026-02-21T19:29:00","comments":"الفجيرةCreated from Application Parser","areaNameAr":"الفجيرة","areaNameEn":"Fujairah","emirateNameAr":"الفجيرة","emirateNameEn":"Fujairah","areaID":52,"emirateID":7,"hijryMonthNameEn":"Ramadhan","hijryMonthNameAr":"رمضان","gMonthNameEn":"February","gMonthNameAr":"فبراير"},{"pid":184897,"gDate":"2026-02-22T00:00:00","dayofWeek":"Sunday","hijryDay":5,"hijryMonth":9,"hijryYear":1447,"emsak":"2026-02-22T05:27:00","fajr":"2026-02-22T05:27:00","shurooq":"2026-02-22T06:41:00","zuhr":"2026-02-22T12:31:00","asr":"2026-02-22T15:46:00","maghrib":"2026-02-22T18:16:00","isha":"2026-02-22T19:30:00","comments":"الفجيرةCreated from Application Parser","areaNameAr":"الفجيرة","areaNameEn":"Fujairah","emirateNameAr":"الفجيرة","emirateNameEn":"Fujairah","areaID":52,"emirateID":7,"hijryMonthNameEn":"Ramadhan","hijryMonthNameAr":"رمضان","gMonthNameEn":"February","gMonthNameAr":"فبراير"},{"pid":184957,"gDate":"2026-02-23T00:00:00","dayofWeek":"Monday","hijryDay":6,"hijryMonth":9,"hijryYear":1447,"emsak":"2026-02-23T05:27:00","fajr":"2026-02-23T05:27:00","shurooq":"2026-02-23T06:40:00","zuhr":"2026-02-23T12:30:00","asr":"2026-02-23T15:47:00","maghrib":"2026-02-23T18:16:00","isha":"2026-02-23T19:30:00","comments":"الفجيرةCreated from Application Parser","areaNameAr":"الفجيرة","areaNameEn":"Fujairah","emirateNameAr":"الفجيرة","emirateNameEn":"Fujairah","areaID":52,"emirateID":7,"hijryMonthNameEn":"Ramadhan","hijryMonthNameAr":"رمضان","gMonthNameEn":"February","gMonthNameAr":"فبراير"},{"pid":185017,"gDate":"2026-02-24T00:00:00","dayofWeek":"Tuesday","hijryDay":7,"hijryMonth":9,"hijryYear":1447,"emsak":"2026-02-24T05:26:00","fajr":"2026-02-24T05:26:00","shurooq":"2026-02-24T06:39:00","zuhr":"2026-02-24T12:30:00","asr":"2026-02-24T15:47:00","maghrib":"2026-02-24T18:17:00","isha":"2026-02-24T19:31:00","comments":"الفجيرةCreated from Application Parser","areaNameAr":"الفجيرة","areaNameEn":"Fujairah","emirateNameAr":"الفجيرة","emirateNameEn":"Fujairah","areaID":52,"emirateID":7,"hijryMonthNameEn":"Ramadhan","hijryMonthNameAr":"رمضان","gMonthNameEn":"February","gMonthNameAr":"فبراير"},{"pid":185077,"gDate":"2026-02-25T00:00:00","dayofWeek":"Wednesday","hijryDay":8,"hijryMonth":9,"hijryYear":1447,"emsak":"2026-02-25T05:25:00","fajr":"2026-02-25T05:25:00","shurooq":"2026-02-25T06:39:00","zuhr":"2026-02-25T12:30:00","asr":"2026-02-25T15:47:00","maghrib":"2026-02-25T18:17:00","isha":"2026-02-25T19:31:00","comments":"الفجيرةCreated from Application Parser","areaNameAr":"الفجيرة","areaNameEn":"Fujairah","emirateNameAr":"الفجيرة","emirateNameEn":"Fujairah","areaID":52,"emirateID":7,"hijryMonthNameEn":"Ramadhan","hijryMonthNameAr":"رمضان","gMonthNameEn":"February","gMonthNameAr":"فبراير"},{"pid":185137,"gDate":"2026-02-26T00:00:00","dayofWeek":"Thursday","hijryDay":9,"hijryMonth":9,"hijryYear":1447,"emsak":"2026-02-26T05:24:00","fajr":"2026-02-26T05:24:00","shurooq":"2026-02-26T06:38:00","zuhr":"2026-02-26T12:30:00","asr":"2026-02-26T15:47:00","maghrib":"2026-02-26T18:18:00","isha":"2026-02-26T19:32:00","comments":"الفجيرةCreated from Application Parser","areaNameAr":"الفجيرة","areaNameEn":"Fujairah","emirateNameAr":"الفجيرة","emirateNameEn":"Fujairah","areaID":52,"emirateID":7,"hijryMonthNameEn":"Ramadhan","hijryMonthNameAr":"رمضان","gMonthNameEn":"February","gMonthNameAr":"فبراير"},{"pid":185197,"gDate":"2026-02-27T00:00:00","dayofWeek":"Friday","hijryDay":10,"hijryMonth":9,"hijryYear":1447,"emsak":"2026-02-27T05:23:00","fajr":"2026-02-27T05:23:00","shurooq":"2026-02-27T06:37:00","zuhr":"2026-02-27T12:30:00","asr":"2026-02-27T15:48:00","maghrib":"2026-02-27T18:19:00","isha":"2026-02-27T19:32:00","comments":"الفجيرةCreated from Application Parser","areaNameAr":"الفجيرة","areaNameEn":"Fujairah","emirateNameAr":"الفجيرة","emirateNameEn":"Fujairah","areaID":52,"emirateID":7,"hijryMonthNameEn":"Ramadhan","hijryMonthNameAr":"رمضان","gMonthNameEn":"February","gMonthNameAr":"فبراير"},{"pid":185257,"gDate":"2026-02-28T00:00:00","dayofWeek":"Saturday","hijryDay":11,"hijryMonth":9,"hijryYear":1447,"emsak":"2026-02-28T05:22:00","fajr":"2026-02-28T05:22:00","shurooq":"2026-02-28T06:36:00","zuhr":"2026-02-28T12:30:00","asr":"2026-02-28T15:48:00","maghrib":"2026-02-28T18:19:00","isha":"2026-02-28T19:33:00","comments":"الفجيرةCreated from Application Parser","areaNameAr":"الفجيرة","areaNameEn":"Fujairah","emirateNameAr":"الفجيرة","emirateNameEn":"Fujairah","areaID":52,"emirateID":7,"hijryMonthNameEn":"Ramadhan","hijryMonthNameAr":"رمضان","gMonthNameEn":"February","gMonthNameAr":"فبراير"}]}